README.txt
setup.py
ravenenv/__init__.py
ravenenv/processors.py
ravenenv.egg-info/PKG-INFO
ravenenv.egg-info/SOURCES.txt
ravenenv.egg-info/dependency_links.txt
ravenenv.egg-info/requires.txt
ravenenv.egg-info/top_level.txt