Metadata-Version: 1.1
Name: ravenenv
Version: 1.0.0
Summary: raven-env is plugging for raven that allow add env variable to contex of a massage
Home-page: http://github.com/cooklee/raven-env
Author: Slawomir Boguslawski
Author-email: sbbogus@gmail.com
License: UNKNOWN
Platform: UNKNOWN
Classifier: Intended Audience :: Developers
Classifier: Intended Audience :: System Administrators
Classifier: Operating System :: OS Independent
Classifier: Topic :: Software Development
Classifier: Programming Language :: Python
Classifier: Programming Language :: Python :: 2.6
Classifier: Programming Language :: Python :: 2.7
Classifier: Programming Language :: Python :: 3.3
Classifier: Programming Language :: Python :: 3.2
